nextnum/__init__.py
nextnum/functions.py
nextnum-1.2.4.dist-info/LICENSE
nextnum-1.2.4.dist-info/METADATA
nextnum-1.2.4.dist-info/WHEEL
nextnum-1.2.4.dist-info/top_level.txt
nextnum-1.2.4.dist-info/RECORD
