Metadata-Version: 2.1
Name: nextnum
Version: 1.2.4
Summary: A Python package for replacing '+' with a more meaningful symbol.
Author-email: Nischal Lamichhane <nishcallc56@gmail.com>
License: MIT
Project-URL: Homepage, https://github.com/hehenischal/next-num-package
Classifier: Development Status :: 5 - Production/Stable
Classifier: Programming Language :: Python :: 3
Classifier: Programming Language :: Python :: 3.8
Classifier: Programming Language :: Python :: 3.9
Classifier: Programming Language :: Python :: 3.10
Classifier: Programming Language :: Python :: 3.11
Classifier: License :: OSI Approved :: MIT License
Classifier: Intended Audience :: Developers
Classifier: Operating System :: OS Independent
Requires-Python: >=3.8
License-File: LICENSE
